Workbook
Name agr: apoio!$E$8
Name ano: app!#REF!
Name apo: app!$D$14
Name con: apoio!$E$4
Name INVmEN: app!#REF!
Name mod: apoio!$E$6
Name patAc10: app!$C$22
Name patAc2: app!$C$20
Name patAc20: app!$C$23
Name patAc30: app!$C$24
Name patAc5: app!$C$21
Name patAcu: app!#REF!
Name rendCart: app!$D$13
Name sal: app!$D$12
Name sugInv: app!#REF!
Name taxMen: app!$D$15

Sheet app
B1: FJM INVEST
B11: CONFIGURAÇÕES E INVESTIMENTO
B12: • Salário | D12: 1000
B13: • Rendimento carteira | D13: 0.006
B14: • Valor investido mensal | D14: 100
B15: • Taxa de rendimento mensal | D15: 0.01079
B16: • Sugestão de investimento | D16: =sal*30% -> 300
B18: CENÁRIOS | D18: DIVIDENDO
B19: Patrimônio acumulado (anos) | D19: MENSAL
A20: 2 | B20: 2 | C20: =FV(taxMen,A20*12,apo)*-1 -> 2722.7627 | D20: =patAc2*rendCart -> 16.336576
A21: 5 | B21: 5 | C21: =FV(taxMen,A21*12,apo)*-1 -> 8377.6914 | D21: =patAc5*rendCart -> 50.266148
A22: 10 | B22: 10 | C22: =FV(taxMen,A22*12,apo)*-1 -> 24328.421 | D22: =patAc10*rendCart -> 145.97053
A23: 20 | B23: 20 | C23: =FV(taxMen,A23*12,apo)*-1 -> 112519.84 | D23: =patAc20*rendCart -> 675.11904
A24: 30 | B24: 30 | C24: =FV(taxMen,A24*12,apo)*-1 -> 432216.97 | D24: =patAc30*rendCart -> 2593.3018
B26: Perfil
B27: Agressivo
B29: TIPOS DE FII | C29: % SUGERIDO | D29: VALORES
B30: PAPEL | C30: =VLOOKUP($B$27&"-"&B30,apoio!B2:C20,2,0) -> 0.5 | D30: =C30*apo -> 50
B31: TIJOLO | C31: =VLOOKUP($B$27&"-"&B31,apoio!B3:C21,2,0) -> 0.1 | D31: =C31*apo -> 10
B32: HIBRIDO | C32: =VLOOKUP($B$27&"-"&B32,apoio!B4:C22,2,0) -> 0.05 | D32: =C32*apo -> 5
B33: FOF | C33: =VLOOKUP($B$27&"-"&B33,apoio!B5:C23,2,0) -> 0.05 | D33: =C33*apo -> 5
B34: DESENVOLVIMENTO | C34: =VLOOKUP($B$27&"-"&B34,apoio!B6:C24,2,0) -> 0.2 | D34: =C34*apo -> 20
B35: HOTELARIA | C35: =VLOOKUP($B$27&"-"&B35,apoio!B7:C25,2,0) -> 0.1 | D35: =C35*apo -> 10
B36: TOTAL | D36: =SUM(D30:D35) -> 100

Sheet apoio
B2: CHAVE | C2: %
B3: =con&"-"&F4 -> Conservador-PAPEL | C3: 0.3 | E3: PERFIL | F3: TIPOS DE FII | G3: %
B4: =con&"-"&F5 -> Conservador-TIJOLO | C4: 0.5 | E4: Conservador | F4: PAPEL | G4: 0
B5: =con&"-"&F6 -> Conservador-HIBRIDO | C5: 0.1 | F5: TIJOLO | G5: 0.05
B6: =con&"-"&F7 -> Conservador-FOF | C6: 0.1 | E6: Moderado | F6: HIBRIDO | G6: 0.08
B7: =con&"-"&F8 -> Conservador-DESENVOLVIMENTO | C7: 0 | F7: FOF | G7: 0.1
B8: =con&"-"&F9 -> Conservador-HOTELARIA | C8: 0 | E8: Agressivo | F8: DESENVOLVIMENTO | G8: 0.2
B9: =mod&"-"&F4 -> Moderado-PAPEL | C9: 0.32 | F9: HOTELARIA | G9: 0.3
B10: =mod&"-"&F5 -> Moderado-TIJOLO | C10: 0.35 | G10: 0.32
B11: =mod&"-"&F6 -> Moderado-HIBRIDO | C11: 0.08 | G11: 0.35
B12: =mod&"-"&F7 -> Moderado-FOF | C12: 0.05 | G12: 0.5
B13: =mod&"-"&F8 -> Moderado-DESENVOLVIMENTO | C13: 0.1
B14: =mod&"-"&F9 -> Moderado-HOTELARIA | C14: 0.1
B15: =agr&"-"&F4 -> Agressivo-PAPEL | C15: 0.5
B16: =agr&"-"&F5 -> Agressivo-TIJOLO | C16: 0.1
B17: =agr&"-"&F6 -> Agressivo-HIBRIDO | C17: 0.05
B18: =agr&"-"&F7 -> Agressivo-FOF | C18: 0.05
B19: =agr&"-"&F8 -> Agressivo-DESENVOLVIMENTO | C19: 0.2
B20: =agr&"-"&F9 -> Agressivo-HOTELARIA | C20: 0.1
